fitpy/__init__.py
fitpy/analysis.py
fitpy/dataset.py
fitpy/plotting.py
fitpy/report.py
fitpy-0.1.2.dist-info/LICENSE
fitpy-0.1.2.dist-info/METADATA
fitpy-0.1.2.dist-info/WHEEL
fitpy-0.1.2.dist-info/top_level.txt
fitpy-0.1.2.dist-info/RECORD
