Metadata-Version: 2.1
Name: fitpy
Version: 0.1.2
Summary: Framework for fitting models to (spectroscopic) data.
Home-page: https://www.fitpy.de/
Author: Till Biskup
Author-email: till@till-biskup.de
Project-URL: Documentation, https://docs.fitpy.de/
Project-URL: Source, https://github.com/tillbiskup/fitpy
Keywords: fitting,spectroscopy,data processing and analysis,reproducible science,reproducible research,good scientific practice,recipe-driven data analysis
Classifier: Programming Language :: Python :: 3
Classifier: Programming Language :: Python :: 3.7
Classifier: Programming Language :: Python :: 3.8
Classifier: Programming Language :: Python :: 3.9
Classifier: License :: OSI Approved :: BSD License
Classifier: Operating System :: OS Independent
Classifier: Intended Audience :: Science/Research
Classifier: Development Status :: 4 - Beta
Classifier: Topic :: Scientific/Engineering
Requires-Python: >=3.7
License-File: LICENSE
Requires-Dist: aspecd>0.9.0
Requires-Dist: numpy
Requires-Dist: scipy>=1.7.0
Requires-Dist: lmfit
Provides-Extra: dev
Requires-Dist: prospector; extra == "dev"
Requires-Dist: pyroma; extra == "dev"
Requires-Dist: bandit; extra == "dev"
Requires-Dist: black; extra == "dev"
Provides-Extra: docs
Requires-Dist: sphinx; extra == "docs"
Requires-Dist: sphinx_rtd_theme; extra == "docs"
Requires-Dist: sphinx-multiversion; extra == "docs"
Provides-Extra: deployment
Requires-Dist: build; extra == "deployment"
Requires-Dist: twine; extra == "deployment"
